progimage/__init__.py
progimage/image.py
progimage/test_image.py
progimage_lib-0.1.0.dist-info/METADATA
progimage_lib-0.1.0.dist-info/WHEEL
progimage_lib-0.1.0.dist-info/top_level.txt
progimage_lib-0.1.0.dist-info/RECORD
