Metadata-Version: 2.1
Name: progimage-lib
Version: 0.1.0
Summary: Python package for ProgImage
Home-page: https://github.com/chitnguyen169/progimage-lib
Author: Chi Nguyen
Author-email: chi.nguyen.gmb@gmail.com
Classifier: Programming Language :: Python :: 3
Classifier: License :: OSI Approved :: MIT License
Classifier: Operating System :: OS Independent
Requires-Dist: requests (==2.27.1)
